README.rst
setup.py
pysniper.egg-info/PKG-INFO
pysniper.egg-info/SOURCES.txt
pysniper.egg-info/dependency_links.txt
pysniper.egg-info/entry_points.txt
pysniper.egg-info/not-zip-safe
pysniper.egg-info/requires.txt
pysniper.egg-info/top_level.txt
sniper/__init__.py
sniper/constants.py
sniper/errors.py
sniper/main.py
sniper/parser.py
sniper/sniper.py
sniper/utilities.py
sniper/version.py