Metadata-Version: 1.0
Name: pysniper
Version: 1.0.0
Summary: Sniper is a clould enabled, terminal based easy to use snippet manager.
Home-page: UNKNOWN
Author: HashCode55
Author-email: mehul.ahuja09@gmail.com
License: MIT License
Platform: UNKNOWN
